[{"date": "May-20-2022", "time": "8:29", "action": "Access Data"}, {"date": "May-20-2022", "time": "8:37", "action": "Access Data"}, {"date": "May-20-2022", "time": "8:59", "action": "Access Data"}, {"date": "May-20-2022", "time": "8:59", "action": "Filter data by deptartment: Accounting"}, {"date": "May-20-2022", "time": "9:0", "action": "Filter data by deptartment: asd"}, {"date": "May-20-2022", "time": "9:1", "action": "Filter data by deptartment: Accounting"}, {"date": "May-20-2022", "time": "9:3", "action": "Filter data by deptartment: Accounting"}, {"date": "May-20-2022", "time": "9:5", "action": "Filter data by deptartment: Accounting"}, {"date": "May-20-2022", "time": "9:5", "action": "Filter data by deptartment: Accounting"}]